{"event":[{"id":"147","start_date":"2013-11-15 00:00:00","show_time":null,"title":"Jouer : Un cadeau pour nos familles","link":{"title":"Plus d'info","link":"https:\/\/www.facebook.com\/events\/408473755942803\/?ref_dashboard_filter=upcoming"},"extra_info":"Jouer est un cadeau<br>\n Anim\u00e9e par Pascal DERU, auteur du livre \"Jouer vous va si bien\"<br>\nUne conf\u00e9rence concr\u00e8te et pleine de bo\u00eetes qui s'ouvrent. Un rendez-vous joyeux dont on ressort \u00e9tonn\u00e9.<br><br>\nVendredi 15 novembre - 20h30 - Ecole Jacques Pr\u00e9vert Villeneuve d'Ascq","end_date":"2013-11-15 22:00:00","connections_id":0,"image":"http:\/\/www.kidzou.fr\/wp-content\/uploads\/2013\/10\/Jouer_Conf\u00e9rence.jpg","address":"Rue de la Pr\u00e9v\u00f4t\u00e9, 59650 Villeneuve-d'Ascq","venue":"Villeneuve d'Ascq","featured":"0","extra_venue":"0","modification_date":"2013-10-24 20:41:26","connections_timestamp":1356998400,"organization":null,"addresses":null,"options":null,"post_name":"","post_title":"","event_timestamp":1382647286,"connections_adresse":"","connections_options":"","dates_teaser":"Du 15\/11 au 15\/11"}]}