{"event":[{"id":"217","start_date":"2014-01-08 00:00:00","show_time":"0","title":"Plan\u00e9tarium","link":{"title":"Plus d'info","link":"http:\/\/www.forumdepartementaldessciences.fr\/planetarium\/planning-des-seances-periode-scolaire\/"},"extra_info":"Plan\u00e9tarium : S\u00e9ances des mercredis du mois de janvier\r\n<ul>\r\n\t<li>11h00 \u2013 L\u2019oreille dans les \u00e9toiles -\u00a0\u00a0\u00e0 partir de 7 ans<\/li>\r\n\t<li>15h00 \u2013 Poussi\u00e8re de Lune -\u00a0conte pour enfants \u00e0 partir de 5 ans<\/li>\r\n\t<li>16h30 \u2013 Les \u00e9toiles d\u2019Hercule -\u00a0\u00a0\u00e0 partir de 7 ans<\/li>\r\n<\/ul>\r\nS\u00e9ance d\u2019environ 1h - 5\u20ac, tarif r\u00e9duit 3\u20ac, 2\u20ac pour les moins de 18 ans\r\n\r\nAu Forum des Sciences \u00e0 Villeneuve d\\'Ascq","end_date":"2014-01-08 23:00:00","connections_id":"9","image":"http:\/\/www.kidzou.fr\/wp-content\/uploads\/2013\/12\/planetarium.jpg","address":"","venue":"","featured":"0","extra_venue":"0","modification_date":"2013-12-22 19:30:01","validated":"1","customer":"0","connections_timestamp":1381529526,"organization":"Forum D\u00e9partemental des Sciences","addresses":"a:1:{s:32:\"010b10439ecd5a2522e18ee39df77902\";a:14:{s:4:\"type\";s:4:\"work\";s:10:\"visibility\";s:6:\"public\";s:6:\"line_1\";s:30:\"1 place de l\u2019H\u00f4tel de ville\";s:6:\"line_2\";s:0:\"\";s:6:\"line_3\";s:0:\"\";s:4:\"city\";s:19:\"Villeneuve d\u2019Ascq\";s:5:\"state\";s:0:\"\";s:7:\"zipcode\";s:5:\"59650\";s:7:\"country\";s:0:\"\";s:8:\"latitude\";N;s:9:\"longitude\";N;s:2:\"id\";s:2:\"10\";s:5:\"order\";i:0;s:9:\"preferred\";b:0;}}","options":"a:4:{s:5:\"entry\";a:1:{s:4:\"type\";s:12:\"organization\";}s:5:\"group\";a:1:{s:6:\"family\";a:0:{}}s:4:\"logo\";a:3:{s:6:\"linked\";b:1;s:7:\"display\";b:1;s:4:\"name\";s:23:\"Forum-sciences_logo.jpg\";}s:5:\"image\";a:3:{s:6:\"linked\";b:0;s:7:\"display\";b:0;s:4:\"name\";a:4:{s:9:\"thumbnail\";N;s:5:\"entry\";N;s:7:\"profile\";N;s:8:\"original\";N;}}}","post_name":"forum-departemental-des-sciences","post_title":"Forum d\u00e9partemental des Sciences","event_timestamp":1387740601,"connections_adresse":{"line_1":"1 place de l\u2019H\u00f4tel de ville","line_2":"","line_3":"","city":"Villeneuve d\u2019Ascq","zipcode":"59650","latitude":null,"longitude":null},"connections_options":{"entry":{"type":"organization"},"group":{"family":[]},"logo":{"linked":true,"display":true,"name":"Forum-sciences_logo.jpg"},"image":{"linked":false,"display":false,"name":{"thumbnail":null,"entry":null,"profile":null,"original":null}}},"dates_teaser":"Du 08\/01 au 08\/01"}]}