{"event":[{"id":"58","start_date":"2013-11-07 00:00:00","show_time":"0","title":"Rencontres Parentales","link":{"title":"Plus d'info","link":"http:\/\/isabelleprugnaud.com\/ateliers\/"},"extra_info":"RENCONTRES PARENTALES\u00a0Anim\u00e9es par Isabelle Prugnaud.\r\n<br\/><br\/>\r\nJeudi 7 novembre 2013, de 20h \u00e0 22h : Comment accompagner la col\u00e8re de l\u2019enfant\u2026.\r\n<br\/><br\/>\r\nRencontre entre parents pour \u00e9changer et partager sur diff\u00e9rents th\u00e8mes.\u00a0Chacun peut s\u2019exprimer librement, faire part de ses exp\u00e9riences, de son ressenti face \u00e0 une situation.\r\n<br\/><br\/>\r\nNombre de places \u00e9tant limit\u00e9 (7 personnes max), r\u00e9servation au 06 14 67 38 82.\r\nParticipation de 12 euros, 18 euros pour un couple.\r\nLieu : Villeneuve d\\'Ascq (adresse communiqu\u00e9e lors de la r\u00e9servation)\r\n<br\/><br\/>\r\n<strong>Gagnez une place<\/strong> en participant au concours le jeudi soir pr\u00e9c\u00e9dant la rencontre, \u00e0 20h sur la Page Facebook de Kidzou : http:\/\/www.facebook.com\/kidzou","end_date":"2013-11-07 22:00:00","connections_id":0,"image":"http:\/\/www.kidzou.fr\/wp-content\/uploads\/2013\/09\/mainsloicanais1.jpg","address":"59650 Villeneuve d\\'Ascq, France","venue":"Villeneuve d\\'Ascq","featured":"0","extra_venue":"1","modification_date":"2013-11-05 20:06:43","connections_timestamp":1356998400,"organization":null,"addresses":null,"options":null,"post_name":"","post_title":"","event_timestamp":1383682003,"connections_adresse":"","connections_options":"","dates_teaser":"Du 07\/11 au 07\/11"}]}